thinknum/History.py
thinknum/Query.py
thinknum/__init__.py
thinknum-2.0.0.dist-info/LICENSE.txt
thinknum-2.0.0.dist-info/METADATA
thinknum-2.0.0.dist-info/WHEEL
thinknum-2.0.0.dist-info/top_level.txt
thinknum-2.0.0.dist-info/RECORD
