Metadata-Version: 2.1
Name: thinknum
Version: 2.0.0
Home-page: https://www.thinknum.com/demo/
Download-URL: https://github.com/thinknum/thinknum-client
Author: Thinknum
Author-email: customersuccess@thinknum.com
License: MIT
Keywords: Thinknum,Alternative data,Data
Classifier: Development Status :: 5 - Production/Stable
Classifier: Intended Audience :: Developers
Classifier: Topic :: Software Development :: Build Tools
Classifier: License :: OSI Approved :: MIT License
Classifier: Programming Language :: Python :: 2
Classifier: Programming Language :: Python :: 3
Classifier: Programming Language :: Python :: 3.4
Classifier: Programming Language :: Python :: 3.5
Classifier: Programming Language :: Python :: 3.6
License-File: LICENSE.txt
Requires-Dist: requests
